pthon_package/__init__.py
harshavardhan_test-0.1.dist-info/METADATA
harshavardhan_test-0.1.dist-info/WHEEL
harshavardhan_test-0.1.dist-info/top_level.txt
harshavardhan_test-0.1.dist-info/RECORD
