Metadata-Version: 2.1
Name: harshavardhan-test
Version: 0.1
Summary: This is an Example Package
Home-page: https://github.com/harshavardhanm03/python_package
Author: Me
Author-email: harshavardhanm03@gmail.com
License: MIT
Keywords: hello world example examples
Platform: UNKNOWN
